PyVuka/__init__.py
PyVuka/app.py
PyVuka/commands.py
PyVuka/data_obj.py
PyVuka/fileio.py
PyVuka/fitfxns.py
PyVuka/inputprocessing.py
PyVuka/numericalmethods.py
PyVuka/plot.py
PyVuka/pyvuka.py
PyVuka/svd.py
PyVuka/ModuleLink/__init__.py
PyVuka/ModuleLink/toPyVuka.py
PyVuka/Modules/__init__.py
PyVuka/Modules/example.py
PyVuka-0.1.1.3.dist-info/LICENSE
PyVuka-0.1.1.3.dist-info/METADATA
PyVuka-0.1.1.3.dist-info/WHEEL
PyVuka-0.1.1.3.dist-info/top_level.txt
PyVuka-0.1.1.3.dist-info/RECORD
