Metadata-Version: 2.1
Name: PyVuka
Version: 0.1.1.3
Summary: A General Purpose Global Data Analysis Package
Home-page: https://github.com/bostonautolytics/pyvuka
Author: R. Paul Nobrega
Author-email: Paul@BostonAutoLytics.com
License: UNKNOWN
Platform: UNKNOWN
Classifier: Programming Language :: Python :: 3
Classifier: License :: Free For Educational Use
Classifier: Operating System :: OS Independent
Requires-Python: >=3.10
License-File: LICENSE
Requires-Dist: Pillow >=10.2.0
Requires-Dist: XlsxWriter >=3.2.0
Requires-Dist: asteval >=0.9.32
Requires-Dist: chardet >=5.2.0
Requires-Dist: lmfit >=1.2.2
Requires-Dist: matplotlib >=3.8.3
Requires-Dist: numpy >=1.26.4
Requires-Dist: psutil >=5.9.8
Requires-Dist: scipy >=1.12.0
Requires-Dist: xlrd >=2.0.1
